confidential_ml_utils/__init__.py
confidential_ml_utils/constants.py
confidential_ml_utils/exceptions.py
confidential_ml_utils/logging.py
confidential_ml_utils/stack_trace_extractor.py
confidential_ml_utils-0.9.1.dist-info/LICENSE
confidential_ml_utils-0.9.1.dist-info/METADATA
confidential_ml_utils-0.9.1.dist-info/WHEEL
confidential_ml_utils-0.9.1.dist-info/top_level.txt
confidential_ml_utils-0.9.1.dist-info/RECORD
