Metadata-Version: 2.1
Name: confidential-ml-utils
Version: 0.9.1
Summary: Utilities for confidential machine learning
Home-page: https://github.com/Azure/confidential-ml-utils
Author: AML Data Science
Author-email: aml-ds@microsoft.com
License: MIT
Platform: UNKNOWN
Classifier: License :: OSI Approved :: MIT License
Classifier: Programming Language :: Python :: 3
Classifier: Programming Language :: Python :: 3.6
Classifier: Programming Language :: Python :: 3.7
Classifier: Programming Language :: Python :: 3.8
Classifier: Programming Language :: Python :: 3.9
Classifier: Programming Language :: Python :: 3.10
Requires-Python: ~=3.6
